odoo/addons/mgmtsystem_evaluation/README.rst
odoo/addons/mgmtsystem_evaluation/__init__.py
odoo/addons/mgmtsystem_evaluation/__manifest__.py
odoo/addons/mgmtsystem_evaluation/data/cron.xml
odoo/addons/mgmtsystem_evaluation/demo/demo.xml
odoo/addons/mgmtsystem_evaluation/i18n/es.po
odoo/addons/mgmtsystem_evaluation/i18n/it.po
odoo/addons/mgmtsystem_evaluation/i18n/mgmtsystem_evaluation.pot
odoo/addons/mgmtsystem_evaluation/models/__init__.py
odoo/addons/mgmtsystem_evaluation/models/ir_model.py
odoo/addons/mgmtsystem_evaluation/models/mgmtsystem_evaluation.py
odoo/addons/mgmtsystem_evaluation/models/mgmtsystem_evaluation_abstract.py
odoo/addons/mgmtsystem_evaluation/models/mgmtsystem_evaluation_result.py
odoo/addons/mgmtsystem_evaluation/models/mgmtsystem_evaluation_template.py
odoo/addons/mgmtsystem_evaluation/models/res_partner.py
odoo/addons/mgmtsystem_evaluation/readme/CONTRIBUTORS.rst
odoo/addons/mgmtsystem_evaluation/readme/DESCRIPTION.rst
odoo/addons/mgmtsystem_evaluation/readme/USAGE.rst
odoo/addons/mgmtsystem_evaluation/security/ir.model.access.csv
odoo/addons/mgmtsystem_evaluation/security/security.xml
odoo/addons/mgmtsystem_evaluation/static/description/icon.png
odoo/addons/mgmtsystem_evaluation/static/description/index.html
odoo/addons/mgmtsystem_evaluation/static/src/components/evaluation_reference/evaluation_reference.js
odoo/addons/mgmtsystem_evaluation/templates/asset_backend.xml
odoo/addons/mgmtsystem_evaluation/tests/__init__.py
odoo/addons/mgmtsystem_evaluation/tests/test_evaluation.py
odoo/addons/mgmtsystem_evaluation/views/mgmtsystem_evaluation.xml
odoo/addons/mgmtsystem_evaluation/views/mgmtsystem_evaluation_result.xml
odoo/addons/mgmtsystem_evaluation/views/mgmtsystem_evaluation_template.xml
odoo/addons/mgmtsystem_evaluation/views/res_partner.xml
odoo14_addon_mgmtsystem_evaluation-14.0.1.0.3.dist-info/METADATA
odoo14_addon_mgmtsystem_evaluation-14.0.1.0.3.dist-info/WHEEL
odoo14_addon_mgmtsystem_evaluation-14.0.1.0.3.dist-info/top_level.txt
odoo14_addon_mgmtsystem_evaluation-14.0.1.0.3.dist-info/RECORD
